unishell_win/__init__.py
unishell_win/regedit/__init__.py
unishell_win/regedit/reg_types.py
unishell_win/regedit/core/AutoRun.py
unishell_win/regedit/core/AutoRunOnce.py
unishell_win/regedit/core/Environment.py
unishell_win/regedit/core/FileType.py
unishell_win/regedit/core/PATH.py
unishell_win/regedit/core/Registry.py
unishell_win/regedit/core/UserType.py
unishell_win/regedit/core/__init__.py
unishell_win-2.3.3.dist-info/licenses/LICENSE
unishell_win-2.3.3.dist-info/METADATA
unishell_win-2.3.3.dist-info/WHEEL
unishell_win-2.3.3.dist-info/top_level.txt
unishell_win-2.3.3.dist-info/RECORD
