Metadata-Version: 2.4
Name: unishell_win
Version: 2.3.3
Summary: Core cross-platform Python library for filesystem operations
Author: GimpNiK
License-Expression: MIT
Project-URL: Homepage, https://github.com/GimpNiK/UniShell
Project-URL: Documentation, https://github.com/GimpNiK/UniShell
Project-URL: Repository, https://github.com/GimpNiK/UniShell
Project-URL: Issues, https://github.com/GimpNiK/UniShell/issues
Keywords: file,directory,archive,encoding,filesystem,windows,registry,shell,unix,cmd
Classifier: Intended Audience :: Developers
Classifier: Operating System :: OS Independent
Classifier: Operating System :: Microsoft :: Windows
Classifier: Operating System :: POSIX :: Linux
Classifier: Operating System :: MacOS
Classifier: Programming Language :: Python :: 3
Classifier: Programming Language :: Python :: 3.10
Classifier: Programming Language :: Python :: 3.11
Classifier: Programming Language :: Python :: 3.12
Classifier: Topic :: Software Development :: Libraries :: Python Modules
Classifier: Topic :: System :: Filesystems
Classifier: Topic :: Utilities
Requires-Python: >=3.10
License-File: LICENSE
Requires-Dist: unishell>=2.3.3
Dynamic: license-file
